dynalglib/__init__.py
dynalglib/coin_change.py
dynalglib/fibonacci.py
dynalglib/item.py
dynalglib/knapsack.py
dynalglib/resource_allocation.py
dynalglib/tsp.py
dynalglib/utils.py
dynalglib-1.3.dist-info/LICENSE
dynalglib-1.3.dist-info/METADATA
dynalglib-1.3.dist-info/WHEEL
dynalglib-1.3.dist-info/top_level.txt
dynalglib-1.3.dist-info/RECORD
