Metadata-Version: 2.1
Name: dynalglib
Version: 1.3
Summary: Dynalglib is a library which is designed to solve problems using dynamic programming algorithms in Python.
Home-page: https://github.com/yslsml/dynalglib
Author: Milana Antonova
Author-email: mmf.antonovam@gmail.com
License: MIT
Project-URL: Documentation, https://github.com/yslsml/dynalglib/wiki/Documentation
Project-URL: Source, https://github.com/yslsml/dynalglib
Keywords: math,dynamic algo,algorithms,algorithm,dynamic programming,knapsack problem,knapsack,traveling salesman problem,tsp,resource allocation,fibonacci,coin change
Classifier: Development Status :: 3 - Alpha
Classifier: Intended Audience :: Developers
Classifier: Topic :: Software Development :: Build Tools
Classifier: License :: OSI Approved :: MIT License
Classifier: Programming Language :: Python :: 3.7
Classifier: Programming Language :: Python :: 3.8
Classifier: Programming Language :: Python :: 3.9
Classifier: Programming Language :: Python :: 3.10
License-File: LICENSE
